wireguard4netns-0.1.6.dist-info/RECORD
wireguard4netns-0.1.6.dist-info/WHEEL
wireguard4netns-0.1.6.dist-info/LICENSE
wireguard4netns-0.1.6.dist-info/entry_points.txt
wireguard4netns-0.1.6.dist-info/METADATA
wireguard4netns-0.1.6.dist-info/LICENSES/0BSD.txt
wireguard4netns-0.1.6.dist-info/LICENSES/MIT.txt
wireguard4netns/tundev.py
wireguard4netns/__main__.py
wireguard4netns/wireguard_daemon.py
wireguard4netns/py.typed
wireguard4netns/__init__.py
wireguard4netns/wireguard-go
wireguard4netns/cli.py
