Metadata-Version: 2.1
Name: wireguard4netns
Version: 0.1.6
Summary: WireGuard VPN networking for unprivileged network namespaces
Home-page: https://github.com/cmusatyalab/wireguard4netns
License: MIT
Author: Carnegie Mellon University
Author-email: satya+group@cs.cmu.edu
Requires-Python: >=3.7,<4.0
Classifier: Development Status :: 4 - Beta
Classifier: Environment :: Console
Classifier: Intended Audience :: Developers
Classifier: License :: OSI Approved :: MIT License
Classifier: Programming Language :: Python :: 3
Classifier: Programming Language :: Python :: 3.7
Classifier: Programming Language :: Python :: 3.8
Classifier: Programming Language :: Python :: 3.9
Classifier: Programming Language :: Python :: 3.10
Classifier: Programming Language :: Python :: 3.11
Requires-Dist: attrs (>=22.1.0)
Requires-Dist: importlib-resources (>=5.0,<6.0)
Requires-Dist: pyroute2 (>=0.7.3,<0.8.0)
Requires-Dist: typing-extensions (>=4.4.0,<5.0.0) ; python_version < "3.8"
Requires-Dist: wireguard-tools (>=0.4.0,<0.5.0)
Project-URL: Repository, https://github.com/cmusatyalab/wireguard4netns
